README
setup.py
PyHMM.egg-info/PKG-INFO
PyHMM.egg-info/SOURCES.txt
PyHMM.egg-info/dependency_links.txt
PyHMM.egg-info/top_level.txt
src/__init__.py
src/backward.py
src/dhmm_demo.py
src/dhmm_demo_multiple.py
src/dhmm_em.py
src/em_converged.py
src/evaluate_pdf_cond_multinomial.py
src/forward.py
src/forward_backward.py
src/forward_backward2.py
src/mhmm_em.py
src/sample.py
src/underflow_normalize.py
src/viterbi_path.py